README.md
setup.py
genpac_server/__init__.py
genpac_server/build.py
genpac_server/utils.py
genpac_server/views.py
genpac_server.egg-info/PKG-INFO
genpac_server.egg-info/SOURCES.txt
genpac_server.egg-info/dependency_links.txt
genpac_server.egg-info/requires.txt
genpac_server.egg-info/top_level.txt
genpac_server/static/jquery-1.10.2.min.js
genpac_server/static/style.css
genpac_server/templates/base.html
genpac_server/templates/index.html
genpac_server/templates/rules.html