Metadata-Version: 2.1
Name: genpac-server
Version: 1.0b5
Summary: web server for genpac.
Home-page: https://github.com/JinnLynn/genpac-server
Author: JinnLynn
Author-email: eatfishlin@gmail.com
License: MIT
Keywords: proxy pac gfwlist gfw
Platform: any
Classifier: License :: OSI Approved :: MIT License
Classifier: Programming Language :: Python :: 2
Classifier: Programming Language :: Python :: 2.7
